freedata/__init__.py
freedata/freedata.py
freeqd-0.0.1.dist-info/LICENSE
freeqd-0.0.1.dist-info/METADATA
freeqd-0.0.1.dist-info/WHEEL
freeqd-0.0.1.dist-info/top_level.txt
freeqd-0.0.1.dist-info/RECORD
