Metadata-Version: 2.1
Name: freeqd
Version: 0.0.1
Summary: Free quantitative data api which will be built during the next few months.
Home-page: https://github.com/pypa/sampleproject
Author: Warren_zhao
Author-email: nobody010101010101010101@gmail.com
License: UNKNOWN
Project-URL: Bug Tracker, https://github.com/pypa/sampleproject/issues
Platform: UNKNOWN
Classifier: Programming Language :: Python :: 3
Classifier: License :: OSI Approved :: MIT License
Classifier: Operating System :: OS Independent
Requires-Python: >=3.6
License-File: LICENSE
